{
  "hash": {
    "id": 1244,
    "targetTitle": "Федоров А. В.",
    "fullTitle": "Федоров Алексей Викторович",
    "scheduleTarget": 2,
    "iCalLink": "https://schedule-of.mirea.ru/schedule/api/ical/2/1244",
    "scheduleImageLink": "https://schedule-of.mirea.ru/schedule/genericschedule?type=2&id=1244&asImage=True",
    "scheduleUpdateImageLink": "https://schedule-of.mirea.ru/schedule/genericupdate?type=2&id=1244&asImage=True"
  },
  "version": {
    "hashVersion": 3,
    "hash": "+VwlsvP/+7wE4SfiNGcbVg5KJvM/2w0w9/VO0cX14/MOpCbHRwPz6eEdQprmH1ZH6X/GkRwdty64UhMVrzfPKw=="
  }
}