{
  "hash": {
    "id": 91,
    "targetTitle": "Гродзенский Я. С.",
    "fullTitle": "Гродзенский Яков Сергеевич",
    "scheduleTarget": 2,
    "iCalLink": "https://schedule-of.mirea.ru/schedule/api/ical/2/91",
    "scheduleImageLink": "https://schedule-of.mirea.ru/schedule/genericschedule?type=2&id=91&asImage=True",
    "scheduleUpdateImageLink": "https://schedule-of.mirea.ru/schedule/genericupdate?type=2&id=91&asImage=True"
  },
  "version": {
    "hashVersion": 3,
    "hash": "Y95q/66EKKO2NGRZlnhTFvtEk233hB7hXdP2in7sVI2SsjCh5jTD8S4eI0fyIJtuanvzHdCPIZjVwL32ANwjBA=="
  }
}