{
  "hash": {
    "id": 760,
    "targetTitle": "ИКБО-72-23",
    "fullTitle": "ИКБО-72-23",
    "scheduleTarget": 1,
    "iCalLink": "https://schedule-of.mirea.ru/schedule/api/ical/1/760",
    "scheduleImageLink": "https://schedule-of.mirea.ru/schedule/genericschedule?type=1&id=760&asImage=True",
    "scheduleUpdateImageLink": "https://schedule-of.mirea.ru/schedule/genericupdate?type=1&id=760&asImage=True"
  },
  "version": {
    "hashVersion": 3,
    "hash": "Z0d5TMHOLlsrwyRmafvl9+3n7m5FnM74s4+R8hQsm+l48+yZ+GNQq8mGZihh1n6W1zQFdcbJm+Zewr602TeTzw=="
  }
}