{
  "hash": {
    "id": 262,
    "targetTitle": "Леонов Д. А.",
    "fullTitle": "Леонов Дмитрий Алексеевич",
    "scheduleTarget": 2,
    "iCalLink": "https://schedule-of.mirea.ru/schedule/api/ical/2/262",
    "scheduleImageLink": "https://schedule-of.mirea.ru/schedule/genericschedule?type=2&id=262&asImage=True",
    "scheduleUpdateImageLink": "https://schedule-of.mirea.ru/schedule/genericupdate?type=2&id=262&asImage=True"
  },
  "version": {
    "hashVersion": 3,
    "hash": "AIgjGCdzy5WxBaTLSyzah21IgHuf3pFfFy6WCg6KWlEPS2Na0nplgMGwL8XzHuIiyVKJJt6zuP24tixCPbOG2w=="
  }
}