{
  "hash": {
    "id": 52,
    "targetTitle": "Дистанционно (СДО)",
    "fullTitle": "Дистанционно (СДО)",
    "scheduleTarget": 3,
    "iCalLink": "https://schedule-of.mirea.ru/schedule/api/ical/3/52",
    "scheduleImageLink": "https://schedule-of.mirea.ru/schedule/genericschedule?type=3&id=52&asImage=True",
    "scheduleUpdateImageLink": "https://schedule-of.mirea.ru/schedule/genericupdate?type=3&id=52&asImage=True"
  },
  "version": {
    "hashVersion": 3,
    "hash": "GzpfZcq0mRR3QbXMZR+1bqHwa6SnGTJh6yTA20/PYCoyxNM5/zdHYaAGs1gp0hI6ri3rcYfpbKunfCltUM/Ilg=="
  }
}