{
  "hash": {
    "id": 471,
    "targetTitle": "Мостовской М. В.",
    "fullTitle": "Мостовской Михаил Владимирович",
    "scheduleTarget": 2,
    "iCalLink": "https://schedule-of.mirea.ru/schedule/api/ical/2/471",
    "scheduleImageLink": "https://schedule-of.mirea.ru/schedule/genericschedule?type=2&id=471&asImage=True",
    "scheduleUpdateImageLink": "https://schedule-of.mirea.ru/schedule/genericupdate?type=2&id=471&asImage=True"
  },
  "version": {
    "hashVersion": 3,
    "hash": "P+aU40OAIYAd88WUwAaXA6Z5oc23Lx9GKuoLp0t/Fb4u2druhCMpjWgxnmvGI+VOchXsC/FAcTAOGfKucpS0Fg=="
  }
}