{
  "hash": {
    "id": 1548,
    "targetTitle": "Джинджолия Р. С.",
    "fullTitle": "Джинджолия Рауль Сергеевич",
    "scheduleTarget": 2,
    "iCalLink": "https://schedule-of.mirea.ru/schedule/api/ical/2/1548",
    "scheduleImageLink": "https://schedule-of.mirea.ru/schedule/genericschedule?type=2&id=1548&asImage=True",
    "scheduleUpdateImageLink": "https://schedule-of.mirea.ru/schedule/genericupdate?type=2&id=1548&asImage=True"
  },
  "version": {
    "hashVersion": 3,
    "hash": "GWiIL2baUv+nJ9T9TDlOXIaRKjBG2DDywDaiG6h2PYTIIHmdryTJc7fuV89wktW/lYkQL7B29Na8pUSedMGoQw=="
  }
}