{
  "hash": {
    "id": 803,
    "targetTitle": "КМБО-03-23",
    "fullTitle": "КМБО-03-23",
    "scheduleTarget": 1,
    "iCalLink": "https://schedule-of.mirea.ru/schedule/api/ical/1/803",
    "scheduleImageLink": "https://schedule-of.mirea.ru/schedule/genericschedule?type=1&id=803&asImage=True",
    "scheduleUpdateImageLink": "https://schedule-of.mirea.ru/schedule/genericupdate?type=1&id=803&asImage=True"
  },
  "version": {
    "hashVersion": 3,
    "hash": "+sESyW/uCHEqbICphawtOkAnbxGd+BwxNL1SoQGJIlFcnOMhiwsJJg9CVlWe/h2bAfIn9J7kERLScQnOzIMDQQ=="
  }
}