{
  "hash": {
    "id": 729,
    "targetTitle": "С-409 (В-86)",
    "fullTitle": "С-409 (В-86)",
    "scheduleTarget": 3,
    "iCalLink": "https://schedule-of.mirea.ru/schedule/api/ical/3/729",
    "scheduleImageLink": "https://schedule-of.mirea.ru/schedule/genericschedule?type=3&id=729&asImage=True",
    "scheduleUpdateImageLink": "https://schedule-of.mirea.ru/schedule/genericupdate?type=3&id=729&asImage=True"
  },
  "version": {
    "hashVersion": 3,
    "hash": "DwLfhwE2x3QxSzCqZKGShydbNbd2FtEU47GdTqKkr2WMIEmGtMXIWZO0NWSAPF1NmMFkgB8jvVbXOEI+yORJQQ=="
  }
}