{
  "hash": {
    "id": 1020,
    "targetTitle": "Антонова И. В.",
    "fullTitle": "Антонова Ирина Викторовна",
    "scheduleTarget": 2,
    "iCalLink": "https://schedule-of.mirea.ru/schedule/api/ical/2/1020",
    "scheduleImageLink": "https://schedule-of.mirea.ru/schedule/genericschedule?type=2&id=1020&asImage=True",
    "scheduleUpdateImageLink": "https://schedule-of.mirea.ru/schedule/genericupdate?type=2&id=1020&asImage=True"
  },
  "version": {
    "hashVersion": 3,
    "hash": "mCl2uqsHoNLuXxJDmiIT4DRw89u5ifN3Afo/dnbaUY1wkTmIhQDzSt7ZlNuABXQADwoTDGl5ZSSmsYOYg8owZg=="
  }
}