{
  "hash": {
    "id": 540,
    "targetTitle": "Каданцев В. Н.",
    "fullTitle": "Каданцев Василий Николаевич",
    "scheduleTarget": 2,
    "iCalLink": "https://schedule-of.mirea.ru/schedule/api/ical/2/540",
    "scheduleImageLink": "https://schedule-of.mirea.ru/schedule/genericschedule?type=2&id=540&asImage=True",
    "scheduleUpdateImageLink": "https://schedule-of.mirea.ru/schedule/genericupdate?type=2&id=540&asImage=True"
  },
  "version": {
    "hashVersion": 3,
    "hash": "8oh3hCZH7+L3rUK7iaVAu+/WEDyEzD9fWsdqgiuEatLi2ELj2I2Ec48Rys0SKGNZ4YIakNVOwGeg+Ni3NsOGxw=="
  }
}