{
  "hash": {
    "id": 620,
    "targetTitle": "УИБО-01-22",
    "fullTitle": "УИБО-01-22",
    "scheduleTarget": 1,
    "iCalLink": "https://schedule-of.mirea.ru/schedule/api/ical/1/620",
    "scheduleImageLink": "https://schedule-of.mirea.ru/schedule/genericschedule?type=1&id=620&asImage=True",
    "scheduleUpdateImageLink": "https://schedule-of.mirea.ru/schedule/genericupdate?type=1&id=620&asImage=True"
  },
  "version": {
    "hashVersion": 3,
    "hash": "IUpo84DfJZu191ZTEp6EY0ojntvxXZD4p9XF+E0JzRrlliSOWX7xCjEIaijCzzD5IBaCkDqtuNHOVipGHfh8Vw=="
  }
}