{
  "hash": {
    "id": 431,
    "targetTitle": "О-414 (В-86)",
    "fullTitle": "О-414 (В-86)",
    "scheduleTarget": 3,
    "iCalLink": "https://schedule-of.mirea.ru/schedule/api/ical/3/431",
    "scheduleImageLink": "https://schedule-of.mirea.ru/schedule/genericschedule?type=3&id=431&asImage=True",
    "scheduleUpdateImageLink": "https://schedule-of.mirea.ru/schedule/genericupdate?type=3&id=431&asImage=True"
  },
  "version": {
    "hashVersion": 3,
    "hash": "PuiHN3VjAqRKkZxQ0o1oFCxAfhj0c51Xy83tmqGYpQT9zbT32yVxUwcQ4B1wkiENg8AxIWvCCEmRVYnDwbmenw=="
  }
}