{
  "hash": {
    "id": 104,
    "targetTitle": "Криулин А. А.",
    "fullTitle": "Криулин Артур Андреевич",
    "scheduleTarget": 2,
    "iCalLink": "https://schedule-of.mirea.ru/schedule/api/ical/2/104",
    "scheduleImageLink": "https://schedule-of.mirea.ru/schedule/genericschedule?type=2&id=104&asImage=True",
    "scheduleUpdateImageLink": "https://schedule-of.mirea.ru/schedule/genericupdate?type=2&id=104&asImage=True"
  },
  "version": {
    "hashVersion": 3,
    "hash": "bVu4aJe2xtayjDx2J2JwZjm2yFJKLATboQQjLryANVRkfQWtN2xyQD0x39Dtc9/i0irp+UHV+M5AaGhKXFtsJA=="
  }
}