{
  "hash": {
    "id": 1559,
    "targetTitle": "Себякин Ю. Л.",
    "fullTitle": "Себякин Юрий Львович",
    "scheduleTarget": 2,
    "iCalLink": "https://schedule-of.mirea.ru/schedule/api/ical/2/1559",
    "scheduleImageLink": "https://schedule-of.mirea.ru/schedule/genericschedule?type=2&id=1559&asImage=True",
    "scheduleUpdateImageLink": "https://schedule-of.mirea.ru/schedule/genericupdate?type=2&id=1559&asImage=True"
  },
  "version": {
    "hashVersion": 3,
    "hash": "z18Xx50ZFQYrqB4lzZ6Mk2YlB01wGWGgJMCl+GLlE7ksZV/nHMWwg5YTi/EE8d3eUhlVVzxbSxmViPyKbU6jzA=="
  }
}