{
  "hash": {
    "id": 1255,
    "targetTitle": "Чернышева Н. В.",
    "fullTitle": "Чернышева Наталья Викторовна",
    "scheduleTarget": 2,
    "iCalLink": "https://schedule-of.mirea.ru/schedule/api/ical/2/1255",
    "scheduleImageLink": "https://schedule-of.mirea.ru/schedule/genericschedule?type=2&id=1255&asImage=True",
    "scheduleUpdateImageLink": "https://schedule-of.mirea.ru/schedule/genericupdate?type=2&id=1255&asImage=True"
  },
  "version": {
    "hashVersion": 3,
    "hash": "wWj2Rkz/UvlOt1ErZkc5f19z2B3air4owAYLPjFaCrxbwFYHrJ8laT6LoTvctuCRDESgFuD+75rXBcUXd89LOw=="
  }
}