{
  "hash": {
    "id": 1440,
    "targetTitle": "Чернышова О. В.",
    "fullTitle": "Чернышова Оксана Витальевна",
    "scheduleTarget": 2,
    "iCalLink": "https://schedule-of.mirea.ru/schedule/api/ical/2/1440",
    "scheduleImageLink": "https://schedule-of.mirea.ru/schedule/genericschedule?type=2&id=1440&asImage=True",
    "scheduleUpdateImageLink": "https://schedule-of.mirea.ru/schedule/genericupdate?type=2&id=1440&asImage=True"
  },
  "version": {
    "hashVersion": 3,
    "hash": "E1zhc++XbrA5vIUCRrGpZCreL4zcJhGTglc18Cpz+Sj74B5xvtEmZdWX6dz4hv1m9GGyK2skonYxOuFhvYdXYw=="
  }
}