{
  "hash": {
    "id": 1739,
    "targetTitle": "Миннебаев В. М.",
    "fullTitle": "Миннебаев Вадим Минхатович",
    "scheduleTarget": 2,
    "iCalLink": "https://schedule-of.mirea.ru/schedule/api/ical/2/1739",
    "scheduleImageLink": "https://schedule-of.mirea.ru/schedule/genericschedule?type=2&id=1739&asImage=True",
    "scheduleUpdateImageLink": "https://schedule-of.mirea.ru/schedule/genericupdate?type=2&id=1739&asImage=True"
  },
  "version": {
    "hashVersion": 3,
    "hash": "Mu10uiUM3ywd5paCxaB+o2+yIHIudx5jKOm80vZoQwxI0exOivwgXgBVFR0nT1ktULHrTL+bsK1PUA98oqhnvg=="
  }
}