{
  "hash": {
    "id": 177,
    "targetTitle": "Жемерикин О. И.",
    "fullTitle": "Жемерикин Олег Игоревич",
    "scheduleTarget": 2,
    "iCalLink": "https://schedule-of.mirea.ru/schedule/api/ical/2/177",
    "scheduleImageLink": "https://schedule-of.mirea.ru/schedule/genericschedule?type=2&id=177&asImage=True",
    "scheduleUpdateImageLink": "https://schedule-of.mirea.ru/schedule/genericupdate?type=2&id=177&asImage=True"
  },
  "version": {
    "hashVersion": 3,
    "hash": "HbsNxhqXqVJAllojS0+Seqm1nHwKYfv+jBE4aEjLxaVvh9BUyLw8tlSt6adoaxUk51gCRzsx9awDKikCLmV2wQ=="
  }
}