{
  "hash": {
    "id": 727,
    "targetTitle": "Т-310 (В-86)",
    "fullTitle": "Т-310 (В-86)",
    "scheduleTarget": 3,
    "iCalLink": "https://schedule-of.mirea.ru/schedule/api/ical/3/727",
    "scheduleImageLink": "https://schedule-of.mirea.ru/schedule/genericschedule?type=3&id=727&asImage=True",
    "scheduleUpdateImageLink": "https://schedule-of.mirea.ru/schedule/genericupdate?type=3&id=727&asImage=True"
  },
  "version": {
    "hashVersion": 3,
    "hash": "d5QMCwpzjYohcguCQDu0gm4+UNBorHV8hRNS+PoyW0yq80lu0N2N3xbkQ94oToxaRY3QxgX+rETmKggdRQWx7g=="
  }
}