{
  "hash": {
    "id": 1747,
    "targetTitle": "Рашутин Н. А.",
    "fullTitle": "Рашутин Никита Андреевич",
    "scheduleTarget": 2,
    "iCalLink": "https://schedule-of.mirea.ru/schedule/api/ical/2/1747",
    "scheduleImageLink": "https://schedule-of.mirea.ru/schedule/genericschedule?type=2&id=1747&asImage=True",
    "scheduleUpdateImageLink": "https://schedule-of.mirea.ru/schedule/genericupdate?type=2&id=1747&asImage=True"
  },
  "version": {
    "hashVersion": 3,
    "hash": "8i4wX3iNAYDTUZss1HD86tMPJlzlhrXpOQrIkskRTRGHQ/Fw2kgnPUbatk22s14i49HTJhK83jrjxqX7fe9irw=="
  }
}