{
  "hash": {
    "id": 1681,
    "targetTitle": "Лукьяшин А. В.",
    "fullTitle": "Лукьяшин Антон Викторович",
    "scheduleTarget": 2,
    "iCalLink": "https://schedule-of.mirea.ru/schedule/api/ical/2/1681",
    "scheduleImageLink": "https://schedule-of.mirea.ru/schedule/genericschedule?type=2&id=1681&asImage=True",
    "scheduleUpdateImageLink": "https://schedule-of.mirea.ru/schedule/genericupdate?type=2&id=1681&asImage=True"
  },
  "version": {
    "hashVersion": 3,
    "hash": "YGh7l/rLLiR9zwJ8jplu6X3f7UbxB70wPqt7bRA9jMEmzMBfXz3ybHOmI8n74Vn9RYDfwAs2uHrbdf/rKJGGpw=="
  }
}